yarik_django_auth/__init__.py
yarik_django_auth/apps.py
yarik_django_auth/backends.py
yarik_django_auth/forms.py
yarik_django_auth/middleware.py
yarik_django_auth/urls.py
yarik_django_auth/utils.py
yarik_django_auth/views.py
yarik_django_auth/conf/__init__.py
yarik_django_auth/conf/settings.py
yarik_django_auth-2.0.18.dist-info/licenses/LICENSE
yarik_django_auth-2.0.18.dist-info/METADATA
yarik_django_auth-2.0.18.dist-info/WHEEL
yarik_django_auth-2.0.18.dist-info/top_level.txt
yarik_django_auth-2.0.18.dist-info/RECORD
