Metadata-Version: 2.4
Name: yarik-django-auth
Version: 2.0.18
Summary: Authentication django app.
Author-email: YARIK <yarik@mail.ru>
Classifier: Environment :: Web Environment
Classifier: Framework :: Django
Classifier: Framework :: Django :: 5.2
Classifier: Intended Audience :: Developers
Classifier: License :: OSI Approved :: BSD License
Classifier: Operating System :: OS Independent
Classifier: Programming Language :: Python
Classifier: Programming Language :: Python :: 3
Classifier: Programming Language :: Python :: 3 :: Only
Classifier: Programming Language :: Python :: 3.10
Classifier: Programming Language :: Python :: 3.11
Classifier: Programming Language :: Python :: 3.12
Classifier: Programming Language :: Python :: 3.13
Classifier: Topic :: Internet :: WWW/HTTP
Classifier: Topic :: Internet :: WWW/HTTP :: Dynamic Content
Requires-Python: >=3.11
License-File: LICENSE
Requires-Dist: django>=5.1.7
Requires-Dist: PyJWT==2.9.0
Requires-Dist: asgiref==3.8.1
Requires-Dist: requests==2.32.3
Requires-Dist: cryptography==44.0.1
Dynamic: license-file
